konta_test/__init__.py
konta_test/const.py
konta_test/job.py
konta_test/tasks/__init__.py
konta_test/tasks/data_augumentation.py
konta_test/tasks/machine_translation.py
konta_test-0.1.0.dist-info/METADATA
konta_test-0.1.0.dist-info/WHEEL
konta_test-0.1.0.dist-info/RECORD
