Metadata-Version: 2.1
Name: konta-test
Version: 0.1.0
Summary: 
Author: juhwanlee
Author-email: juhwanlee@diquest.com
Requires-Python: >=3.8,<3.9
Classifier: Programming Language :: Python :: 3
Classifier: Programming Language :: Python :: 3.8
Requires-Dist: torch (==2.0.0)
Requires-Dist: transformers (==4.29.1)
